inputconsole.py
inputconsole-1.0.1.dist-info/LICENSE
inputconsole-1.0.1.dist-info/METADATA
inputconsole-1.0.1.dist-info/WHEEL
inputconsole-1.0.1.dist-info/top_level.txt
inputconsole-1.0.1.dist-info/RECORD
