Metadata-Version: 2.1
Name: inputconsole
Version: 1.0.1
Summary: A console for Python that will keep all output above the input line without interrupting the input line.
Home-page: UNKNOWN
Author: Nathan Fiscaletti
License: UNKNOWN
Platform: UNKNOWN
Classifier: Programming Language :: Python :: 3
Classifier: License :: OSI Approved :: MIT License
Classifier: Operating System :: OS Independent
Requires-Python: >=3.6
Requires-Dist: readchar
